nonebot/adapters/villa/__init__.py
nonebot/adapters/villa/adapter.py
nonebot/adapters/villa/api.py
nonebot/adapters/villa/bot.py
nonebot/adapters/villa/config.py
nonebot/adapters/villa/event.py
nonebot/adapters/villa/exception.py
nonebot/adapters/villa/message.py
nonebot/adapters/villa/models.py
nonebot/adapters/villa/payload.py
nonebot/adapters/villa/pb/__init__.py
nonebot/adapters/villa/pb/command_pb2.py
nonebot/adapters/villa/pb/model_pb2.py
nonebot/adapters/villa/pb/robot_event_message_pb2.py
nonebot/adapters/villa/permission.py
nonebot/adapters/villa/utils.py
nonebot_adapter_villa-1.4.2.dist-info/LICENSE
nonebot_adapter_villa-1.4.2.dist-info/METADATA
nonebot_adapter_villa-1.4.2.dist-info/WHEEL
nonebot_adapter_villa-1.4.2.dist-info/RECORD
