Metadata-Version: 2.1
Name: nonebot-adapter-villa
Version: 1.4.2
Summary: NoneBot2 米游社大别野 Bot 适配器。MiHoYo Villa Bot adapter for nonebot2.
Home-page: https://github.com/CMHopeSunshine/nonebot-adapter-villa
License: MIT
Keywords: nonebot,mihoyo,bot
Author: CMHopeSunshine
Author-email: 277073121@qq.com
Requires-Python: >=3.8,<4.0
Classifier: License :: OSI Approved :: MIT License
Classifier: Programming Language :: Python :: 3
Classifier: Programming Language :: Python :: 3.8
Classifier: Programming Language :: Python :: 3.9
Classifier: Programming Language :: Python :: 3.10
Classifier: Programming Language :: Python :: 3.11
Classifier: Programming Language :: Python :: 3.12
Requires-Dist: nonebot2 (>=2.1.2,<3.0.0)
Requires-Dist: protobuf (>=4.25.1,<5.0.0)
Requires-Dist: rsa (>=4.9,<5.0)
Project-URL: Documentation, https://github.com/CMHopeSunshine/nonebot-adapter-villa
Project-URL: Repository, https://github.com/CMHopeSunshine/nonebot-adapter-villa
